pythern/__init__.py
pythern/about.py
pythern/container.py
pythern/object_factory.py
pythern/singleton.py
pythern-0.0.5.dist-info/LICENSE
pythern-0.0.5.dist-info/METADATA
pythern-0.0.5.dist-info/WHEEL
pythern-0.0.5.dist-info/top_level.txt
pythern-0.0.5.dist-info/RECORD
