Metadata-Version: 2.1
Name: pythern
Version: 0.0.5
Summary: A dependency injection container for python applications
Home-page: https://github.com/abantos/dichotomy
Author: Isaac Rodriguez
Author-email: oss.abantos@outlook.com
License: MIT
Keywords: dependency injection container inversion control
Platform: UNKNOWN
Classifier: Development Status :: 1 - Planning
Classifier: Intended Audience :: Developers
Classifier: License :: OSI Approved :: MIT License
Classifier: Programming Language :: Python
Classifier: Programming Language :: Python :: 3.7
Classifier: Programming Language :: Python :: 3.8
Classifier: Programming Language :: Python :: 3.9
Classifier: Topic :: Software Development :: Libraries
Classifier: Topic :: Software Development :: Libraries :: Application Frameworks
License-File: LICENSE
